aws_member_accnt_manager/__init__.py
aws_member_accnt_manager/index.py
aws_member_accnt_manager/role.py
aws_member_accnt_manager-1.0.dist-info/METADATA
aws_member_accnt_manager-1.0.dist-info/WHEEL
aws_member_accnt_manager-1.0.dist-info/top_level.txt
aws_member_accnt_manager-1.0.dist-info/RECORD
