Metadata-Version: 2.1
Name: aws-member-accnt-manager
Version: 1.0
Summary: Manage member accounts under AWS Organisation with Cloudformation
Home-page: http://github.com/droidlabour
Author: Joy Prakash Sharma
Author-email: droidlabour@gmail.com
License: MIT
Platform: UNKNOWN
Classifier: Development Status :: 3 - Alpha
Classifier: License :: OSI Approved :: MIT License
Classifier: Programming Language :: Python :: 3.7
Requires-Dist: boto3
Requires-Dist: cfnresponse
